{".class": "MypyFile", "_fullname": "utils.torchaudio_methods", "is_partial_stub_package": false, "is_stub": false, "names": {".class": "SymbolTable", "__doc__": {".class": "SymbolTableNode", "kind": "Gdef", "node": {".class": "Var", "flags": ["is_ready"], "fullname": "utils.torchaudio_methods.__doc__", "name": "__doc__", "type": "builtins.str"}}, "__file__": {".class": "SymbolTableNode", "kind": "Gdef", "node": {".class": "Var", "flags": ["is_ready"], "fullname": "utils.torchaudio_methods.__file__", "name": "__file__", "type": "builtins.str"}}, "__name__": {".class": "SymbolTableNode", "kind": "Gdef", "node": {".class": "Var", "flags": ["is_ready"], "fullname": "utils.torchaudio_methods.__name__", "name": "__name__", "type": "builtins.str"}}, "__package__": {".class": "SymbolTableNode", "kind": "Gdef", "node": {".class": "Var", "flags": ["is_ready"], "fullname": "utils.torchaudio_methods.__package__", "name": "__package__", "type": "builtins.str"}}, "draw_spectrogram": {".class": "SymbolTableNode", "kind": "Gdef", "node": {".class": "FuncDef", "arg_kinds": [0, 1, 1], "arg_names": ["waveform", "kind", "output_file"], "flags": [], "fullname": "utils.torchaudio_methods.draw_spectrogram", "name": "draw_spectrogram", "type": null}}, "draw_waveform": {".class": "SymbolTableNode", "kind": "Gdef", "node": {".class": "FuncDef", "arg_kinds": [0, 1], "arg_names": ["waveform", "output_file"], "flags": [], "fullname": "utils.torchaudio_methods.draw_waveform", "name": "draw_waveform", "type": null}}, "plt": {".class": "SymbolTableNode", "kind": "Gdef", "node": {".class": "Var", "flags": ["is_suppressed_import", "is_ready"], "fullname": "utils.torchaudio_methods.plt", "name": "plt", "type": {".class": "AnyType", "missing_import_name": "utils.torchaudio_methods.plt", "source_any": null, "type_of_any": 3}}}, "torchaudio": {".class": "SymbolTableNode", "kind": "Gdef", "node": {".class": "Var", "flags": ["is_suppressed_import", "is_ready"], "fullname": "utils.torchaudio_methods.torchaudio", "name": "torchaudio", "type": {".class": "AnyType", "missing_import_name": "utils.torchaudio_methods.torchaudio", "source_any": null, "type_of_any": 3}}}}, "path": "utils/torchaudio_methods.py"}